{"stats":{"minecraft:crafted":{"minecraft:black_dye":3,"minecraft:jungle_button":14,"minecraft:lever":1,"minecraft:quartz_block":16,"minecraft:emerald":137,"silentgear:saw_blade":1,"minecraft:hay_block":22,"minecraft:campfire":2,"minecraft:iron_pickaxe":1,"minecraft:gold_ingot":238,"iceandfire:dragon_flute":1,"minecraft:bone_meal":55,"minecraft:stone_pickaxe":1,"silentgear:sword":1,"minecraft:wheat":80,"silentgear:saw":1,"sophisticatedbackpacks:gold_backpack":5,"minecraft:iron_shovel":1,"minecraft:oak_planks":71,"minecraft:stone":3,"tombstone:grave_key":2,"minecraft:comparator":1,"minecraft:chest":2,"sophisticatedbackpacks:backpack":2,"minecraft:crafting_table":5,"minecraft:wooden_pickaxe":1,"minecraft:birch_planks":33,"minecraft:paper":66,"minecraft:diamond_pickaxe":1,"minecraft:shield":3,"minecraft:stick":1096,"sophisticatedbackpacks:diamond_backpack":2,"minecraft:iron_ingot":54,"minecraft:redstone_torch":3,"minecraft:netherite_scrap":1,"sophisticatedbackpacks:iron_backpack":2,"minecraft:crimson_planks":1,"minecraft:jungle_wood":2,"minecraft:bucket":4,"minecraft:air":7892,"minecraft:bread":198,"minecraft:jungle_planks":491,"silentgear:hammer":1,"minecraft:acacia_planks":4,"minecraft:torch":12},"minecraft:mined":{"graveyard:pedestal":2,"minecraft:jungle_leaves":4,"graveyard:candle_holder":11,"minecraft:obsidian":4,"alexscaves:limestone":1,"minecraft:granite":95,"minecraft:acacia_log":1,"minecraft:jungle_log":659,"minecraft:coal_block":38,"minecraft:deepslate_bricks":2,"minecraft:oxeye_daisy":1,"minecraft:tall_seagrass":2,"minecraft:spawner":15,"minecraft:polished_blackstone_bricks":33,"minecraft:magma_block":1,"minecraft:barrel":2,"minecraft:fire":146,"minecraft:cobbled_deepslate":9,"minecraft:pumpkin":2,"iceandfire:gold_pile":177,"minecraft:cave_vines":1,"minecraft:polished_deepslate_slab":1,"minecraft:dirt_path":2,"scalinghealth:deepslate_power_crystal_ore":3,"minecraft:stripped_mangrove_wood":1,"minecraft:player_head":1,"minecraft:kelp_plant":8,"minecraft:player_wall_head":4,"graveyard:dark_iron_trapdoor":5,"minecraft:crimson_nylium":10,"minecraft:deepslate_tile_slab":1,"minecraft:torch":6,"minecraft:blast_furnace":1,"minecraft:melon":4,"gobber2:gobber2_lucky_block_nether":7,"undead_revamp2:chiseled_dripstonepillar":2,"minecraft:cyan_bed":3,"minecraft:sugar_cane":41,"minecraft:skeleton_skull":1,"mutantmonsters:mutant_skeleton_skull":1,"minecraft:wheat":6,"minecraft:grass":203,"minecraft:smooth_quartz":1,"minecraft:sandstone_wall":2,"minecraft:acacia_sign":1,"minecraft:deepslate":505,"silentgear:blackstone_crimson_iron_ore":1,"silentgems:deepslate_iolite_ore":1,"minecraft:deepslate_tiles":2,"minecraft:light_gray_stained_glass_pane":6,"farmersdelight:wild_carrots":1,"silentgems:deepslate_peridot_ore":15,"minecraft:nether_bricks":21,"minecraft:dark_oak_fence":2,"minecraft:jungle_planks":5,"born_in_chaos_v1:black_argillite":15,"minecraft:crimson_roots":1,"minecraft:moss_block":6,"minecraft:kelp":10,"born_in_chaos_v1:gnawed_bones":5,"silentgems:deepslate_ruby_ore":10,"minecraft:suspicious_sand":1,"minecraft:andesite":86,"graveyard:sarcophagus":11,"minecraft:vine":27,"minecraft:bamboo":4,"minecraft:soul_sand":3,"minecraft:potted_lily_of_the_valley":1,"silentgems:alexandrite_nether_ore":1,"minecraft:warped_roots":1,"minecraft:copper_ore":20,"minecraft:tall_grass":160,"minecraft:deepslate_gold_ore":22,"minecraft:diorite":198,"minecraft:black_stained_glass":2,"silentgems:deepslate_turquoise_ore":1,"minecraft:birch_leaves":1,"silentgems:deepslate_topaz_ore":12,"minecraft:zombie_head":1,"alexscaves:cycad":1,"minecraft:gravel":3,"minecraft:dripstone_block":13,"minecraft:cobweb":2,"minecraft:stone_bricks":1,"minecraft:fern":42,"undead_revamp2:arapholia":4,"minecraft:oak_sapling":1,"minecraft:cobbled_deepslate_stairs":1,"minecraft:sculk_vein":1,"minecraft:grass_block":38,"sophisticatedbackpacks:iron_backpack":1,"gobber2:gobber2_lucky_block":39,"minecraft:cracked_polished_blackstone_bricks":9,"graveyard:dark_iron_door":1,"minecraft:smooth_stone":1,"minecraft:iron_ore":10,"graveyard:leaning_wither_skeleton":1,"iceandfire:crackled_dirt":1,"silentgear:deepslate_bort_ore":5,"minecraft:skeleton_wall_skull":2,"minecraft:iron_bars":6,"minecraft:azalea":1,"minecraft:deepslate_redstone_ore":10,"minecraft:twisting_vines_plant":2,"minecraft:polished_deepslate_stairs":1,"minecraft:yellow_banner":1,"silentgems:black_diamond_nether_ore":17,"minecraft:jungle_stairs":1,"minecraft:chest":1,"minecraft:nether_quartz_ore":2,"minecraft:cobblestone":53,"graveyard:skeleton_hand":3,"graveyard:lying_skeleton":1,"minecraft:oak_planks":3,"minecraft:wall_torch":9,"boh:spinel_ore_ore":7,"minecraft:birch_log":33,"minecraft:tnt":28,"graveyard:creeper_skeleton":1,"undead_revamp2:chiseleddripstonepillartop":3,"minecraft:oak_log":71,"minecraft:sand":1,"minecraft:dirt":61,"minecraft:ancient_debris":1,"minecraft:netherrack":527,"minecraft:oak_leaves":11,"minecraft:tuff":33,"minecraft:yellow_wall_banner":2,"silentgear:wild_flax_plant":1,"minecraft:potted_wither_rose":1,"minecraft:deepslate_diamond_ore":11,"minecraft:candle":2,"graveyard:acacia_coffin":1,"born_in_chaos_v1:infected_diamond_ore":7,"minecraft:lever":3,"minecraft:black_banner":4,"farmersdelight:tomatoes":1,"minecraft:cracked_nether_bricks":2,"minecraft:crimson_stem":1,"minecraft:large_fern":3,"minecraft:hay_block":61,"graveyard:soul_fire_brazier":10,"minecraft:carrots":8,"minecraft:gold_block":2,"minecraft:bookshelf":14,"minecraft:deepslate_iron_ore":41,"minecraft:stripped_oak_log":1,"minecraft:stripped_jungle_log":3,"alexscaves:curly_fern":8,"minecraft:stone":1477,"minecraft:basalt":4,"silentgems:moldavite_nether_ore":3,"minecraft:crafting_table":1,"minecraft:lectern":1,"silentgems:deepslate_silver_ore":9,"minecraft:quartz_bricks":3,"minecraft:sculk":8,"minecraft:blue_bed":4,"minecraft:black_wall_banner":3,"gobber2:gobber2_lucky_block_deepslate":14,"minecraft:yellow_bed":1,"graveyard:dark_iron_bars":1,"minecraft:coal_ore":4,"graveyard:leaning_skeleton":1,"minecraft:lodestone":1,"minecraft:mossy_stone_bricks":1},"minecraft:killed":{"alexsmobs:lobster":1,"born_in_chaos_v1:restless_spirit":2,"graveyard:wraith":15,"hmag:fortress_keeper":1,"minecraft:skeleton":4,"graveyard:acolyte":3,"alexsmobs:leafcutter_ant":1,"minecraft:chicken":6,"majruszsdifficulty:creeperling":1,"minecraft:tropical_fish":1,"mutantmonsters:mutant_skeleton":1,"minecraft:pillager":11,"minecraft:zombie":38,"born_in_chaos_v1:corpse_fly":5,"enemyexpansion:botfly":7,"minecraft:cow":1,"enemyexpansion:trollenraged":1,"undead_revamp2:thehunter":4,"graveyard:corrupted_vindicator":14,"alexsmobs:raccoon":1,"hmag:skeleton_girl":1,"alexsmobs:seagull":2,"born_in_chaos_v1:firelight":2,"iceandfire:siren":1,"minecraft:husk":7,"undead_revamp2:the_moonflower":2,"enemyexpansion:sprinter":2,"hmag:kobold":1,"undead_revamp2:thesomnolence":5,"born_in_chaos_v1:zombie_clown":1,"minecraft:spider":1,"undead_revamp2:thesmoker":2,"undead_revamp2:therod":1,"alexsmobs:kangaroo":1,"artifacts:mimic":1,"minecraft:pig":6,"born_in_chaos_v1:diamond_termite":7,"undead_revamp2:thebeartamer":1,"alexsmobs:crimson_mosquito":2,"minecraft:trader_llama":1,"born_in_chaos_v1:dread_hound":3,"minecraft:stray":2,"undead_revamp2:theskeeper":1,"alexsmobs:fly":1,"alexsmobs:komodo_dragon":1,"graveyard:corrupted_pillager":5,"minecraft:blaze":1,"born_in_chaos_v1:zombie_clown_not_despawn":1,"boh:ink_demon":2,"enemyexpansion:direwolf":3,"born_in_chaos_v1:maggot":17,"born_in_chaos_v1:baby_spider":5,"undead_revamp2:coppertar":1,"minecraft:drowned":3,"born_in_chaos_v1:corpse_fish":2,"undead_revamp2:sucker":2,"hmag:ghost":3,"born_in_chaos_v1:baby_skeleton":1,"enemyexpansion:huntsman":1},"minecraft:picked_up":{"silentgear:raw_crimson_iron":2,"minecraft:chainmail_boots":2,"minecraft:flower_pot":4,"minecraft:prismarine_shard":8,"minecraft:lead":12,"silentgear:chestplate":4,"minecraft:wither_rose":2,"minecraft:enchanted_book":14,"hmag:ancient_stone":2,"minecraft:golden_sword":1,"minecraft:string":45,"graveyard:sarcophagus":15,"gobber2:gobber2_glass_nether":7,"minecraft:shroomlight":1,"minecraft:gold_nugget":2100,"minecraft:cobbled_deepslate":2921,"minecraft:acacia_sign":3,"hmag:cureberry":5,"minecraft:written_book":1,"minecraft:melon_slice":41,"minecraft:coal_block":38,"silentgems:heliodor_glowrose":2,"silentgear:saw_blueprint":1,"minecraft:golden_helmet":2,"gobber2:gobber2_ingot_nether":2,"artifacts:universal_attractor":4,"born_in_chaos_v1:shattered_skull":1,"minecraft:acacia_log":1,"minecraft:sandstone_wall":17,"silentgems:iolite":2,"iceandfire:lightning_dragon_flesh":3,"minecraft:cherry_log":4,"farmersdelight:chicken_cuts":2,"minecraft:end_crystal":1,"boh:vampire_blood":1,"minecraft:golden_chestplate":1,"mutantmonsters:mutant_skeleton_pelvis":1,"minecraft:yellow_banner":3,"minecraft:zombie_spawn_egg":1,"minecraft:bamboo_block":3,"born_in_chaos_v1:fried_maggot":1,"silentgear:rod":3,"minecraft:tropical_fish":1,"farmersdelight:onion":3,"silentgear:axe_blueprint":1,"iceandfire:fire_dragon_heart":3,"farmersdelight:rope":18,"minecraft:blaze_rod":1,"farmersdelight:melon_juice":1,"minecraft:iron_bars":1,"minecraft:birch_log":35,"minecraft:magma_block":1,"minecraft:mossy_cobblestone_slab":1,"minecraft:feather":80,"minecraft:water_bucket":1,"minecraft:jungle_log":617,"dummmmmmy:target_dummy":2,"minecraft:flint":103,"farmersdelight:cooked_bacon":2,"alexsmobs:cooked_kangaroo_meat":2,"minecraft:twisting_vines":4,"silentgems:citrine":3,"gobber2:gobber2_globette":8,"hmag:exp_berry":7,"minecraft:moss_block":14,"silentgems:moldavite":3,"gobber2:gobber2_staff_ensnarement":1,"iceandfire:dragon_skull_fire":3,"iceandfire:shiny_scales":91,"scalinghealth:enchanted_heart":1,"sophisticatedbackpacks:iron_backpack":1,"iceandfire:lightning_dragon_heart":2,"minecraft:barrel":4,"alexsmobs:animal_dictionary":1,"minecraft:bundle":11,"minecraft:quartz_bricks":3,"minecraft:white_candle":2,"iceandfire:crackled_stone":10,"minecraft:lever":3,"minecraft:granite":89,"alexsmobs:tarantula_hawk_wing_fragment":1,"minecraft:chainmail_helmet":1,"minecraft:golden_horse_armor":4,"minecraft:bread":14,"alexsmobs:maggot":1,"born_in_chaos_v1:rotten_fish":1,"minecraft:dark_oak_fence":4,"minecraft:crimson_roots":1,"iceandfire:raw_silver":2,"iceandfire:siren_tear":1,"sophisticatedbackpacks:gold_backpack":2,"iceandfire:dragon_skull_lightning":7,"minecraft:crafting_table":1,"graveyard:acacia_coffin":1,"iceandfire:witherbone":1,"minecraft:nether_wart":8,"born_in_chaos_v1:seedof_chaos":5,"minecraft:cornflower":1,"born_in_chaos_v1:intoxicating_decoction":2,"minecraft:iron_shovel":5,"graveyard:soul_fire_brazier":11,"silentgems:raw_silver":11,"minecraft:cartography_table":1,"minecraft:beef":6,"born_in_chaos_v1:gnawed_bones":6,"minecraft:jungle_sapling":18,"silentgems:peridot":14,"minecraft:chest":2,"minecraft:piston":4,"minecraft:egg":101,"minecraft:sandstone":1,"minecraft:polished_deepslate_slab":1,"minecraft:stone":13,"minecraft:oak_door":1,"artifacts:charm_of_sinking":2,"alexscaves:cycad":4,"silentgear:fluffy_fabric":1,"farmersdelight:tomato_seeds":3,"minecraft:carrot":34,"minecraft:redstone":51,"minecraft:prismarine_crystals":19,"minecraft:jungle_sign":3,"minecraft:tnt":27,"minecraft:diamond_chestplate":1,"farmersdelight:cooked_chicken_cuts":9,"gobber2:gobber2_gooey_beef_nether":3,"minecraft:hay_block":72,"minecraft:sandstone_stairs":3,"tombstone:essence_of_undeath":1,"minecraft:gold_ingot":13,"minecraft:glow_berries":2,"alexsmobs:kangaroo_meat":1,"minecraft:oxeye_daisy":1,"born_in_chaos_v1:monster_flesh":9,"silentgems:black_diamond":17,"minecraft:jungle_fence":2,"majruszsdifficulty:tattered_helmet":4,"minecraft:filled_map":1,"silentgear:blueprint_package":1,"minecraft:packed_mud":1,"minecraft:oak_log":70,"scalinghealth:bandages":26,"silentgear:hammer_blueprint":1,"minecraft:golden_boots":4,"silentgems:alexandrite":1,"mowziesmobs:wrought_axe":1,"tombstone:gift":3,"mutantmonsters:mutant_skeleton_limb":6,"silentgear:rough_rod":1,"minecraft:blue_bed":4,"minecraft:paper":48,"scalinghealth:medkit":2,"minecraft:white_banner":2,"undead_revamp2:chiseled_dripstonepillar":2,"minecraft:apple":1,"minecraft:stone_bricks":1,"minecraft:kelp":50,"mowziesmobs:foliaath_seed":4,"majruszsdifficulty:tattered_leggings":6,"silentgems:ruby":30,"silentgear:shield":2,"minecraft:stone_pickaxe":1,"minecraft:cobweb":13,"scalinghealth:power_crystal_shard":22,"tombstone:bag_of_seeds":2,"minecraft:glass_bottle":7,"minecraft:iron_sword":3,"silentgems:turquoise":1,"iceandfire:chared_stone":1,"iceandfire:copper_nugget":50,"born_in_chaos_v1:ethereal_spirit":2,"graveyard:skeleton_hand":2,"minecraft:gravel":7,"silentgear:bort":13,"minecraft:slime_ball":8,"born_in_chaos_v1:black_argillite_brick_slab":5,"minecraft:stone_axe":1,"minecraft:diamond_axe":1,"minecraft:warped_roots":3,"alexscaves:cave_map":1,"minecraft:lodestone":1,"minecraft:baked_potato":1,"minecraft:melon_seeds":1,"gobber2:gobber2_goo_nether":2,"minecraft:ender_pearl":16,"hmag:lightning_particle":4,"minecraft:wheat":6,"alexscaves:cave_tablet":8,"boh:spinel":8,"minecraft:potion":4,"tombstone:grave_key":6,"mutantmonsters:mutant_skeleton_skull":3,"minecraft:raw_copper":70,"graveyard:candle_holder":10,"minecraft:iron_leggings":2,"minecraft:experience_bottle":49,"minecraft:zombie_head":3,"farmersdelight:fried_rice":1,"minecraft:smooth_stone":1,"alexsmobs:banana":1,"silentgems:ruby_glowrose":154,"minecraft:azalea":1,"minecraft:smooth_quartz":1,"born_in_chaos_v1:stimulating_decoction":2,"farmersdelight:cabbage_seeds":3,"minecraft:iron_boots":1,"minecraft:tipped_arrow":3,"minecraft:stick":44,"apotheosis:gem":44,"minecraft:polished_deepslate_stairs":1,"minecraft:torch":29,"born_in_chaos_v1:flaming_evil_pumpkin":2,"minecraft:porkchop":3,"iceandfire:rotten_egg":2,"minecraft:pointed_dripstone":2,"tombstone:grave_dust":80,"minecraft:diorite":203,"born_in_chaos_v1:nightmare_claw":3,"tombstone:lollipop":9,"silentgems:rose_quartz_glowrose":10,"gobber2:gobber2_foo":4,"farmersdelight:fried_egg":2,"silentgear:leather_scrap":19,"minecraft:rotten_flesh":415,"alexsmobs:emu_egg":2,"minecraft:obsidian":5,"undead_revamp2:arapholia":11,"minecraft:cobblestone":2517,"minecraft:leather_chestplate":5,"minecraft:andesite":87,"minecraft:golden_leggings":1,"alexscaves:cave_book":3,"minecraft:tuff":49,"minecraft:smooth_sandstone_stairs":5,"graveyard:dark_iron_door":1,"minecraft:lapis_lazuli":7,"minecraft:dirt":254,"minecraft:name_tag":2,"born_in_chaos_v1:monster_skin":3,"minecraft:leather_boots":1,"minecraft:bone":236,"minecraft:bow":4,"gobber2:gobber2_gooey_beef":16,"minecraft:wheat_seeds":134,"minecraft:raw_gold":24,"minecraft:cobbled_deepslate_slab":3,"minecraft:mossy_stone_bricks":1,"minecraft:bamboo":133,"minecraft:oak_planks":17,"silentgear:crimson_iron_ingot":7,"gobber2:gobber2_gooey_bread":13,"gobber2:gobber2_rod_nether":2,"minecraft:cooked_porkchop":11,"silentgear:pickaxe":7,"minecraft:music_disc_13":2,"hmag:soul_powder":14,"minecraft:axolotl_bucket":4,"minecraft:poisonous_potato":1,"minecraft:sand":3,"minecraft:jungle_planks":61,"minecraft:grass_block":1,"minecraft:cyan_bed":3,"minecraft:lily_of_the_valley":1,"minecraft:chiseled_sandstone":1,"farmersdelight:cooked_mutton_chops":4,"minecraft:sugar":28,"born_in_chaos_v1:fire_dust":3,"minecraft:diamond":27,"iceandfire:dragonbone_sword_fire":2,"waystones:waystone":1,"minecraft:cracked_polished_blackstone_bricks":9,"minecraft:crossbow":2,"hmag:burning_core":1,"minecraft:bone_meal":37,"minecraft:golden_apple":4,"minecraft:emerald":10,"scalinghealth:cursed_heart":5,"minecraft:oak_sapling":11,"minecraft:netherrack":1137,"minecraft:oak_leaves":5,"gobber2:gobber2_goo":19,"minecraft:cocoa_beans":15,"majruszsdifficulty:tattered_boots":3,"minecraft:charcoal":2,"born_in_chaos_v1:diamond_termite_shard":16,"minecraft:azure_bluet":1,"minecraft:chicken":35,"minecraft:ladder":1,"silentgems:sapphire_glowrose":2,"minecraft:turtle_helmet":2,"minecraft:wooden_pickaxe":9,"iceandfire:chain":8,"minecraft:cooked_rabbit":1,"minecraft:gold_block":2,"minecraft:shield":1,"minecraft:oak_trapdoor":5,"minecraft:iron_axe":2,"minecraft:item_frame":9,"minecraft:quartz_slab":4,"boh:demonic_soul":4,"graveyard:corruption":64,"minecraft:candle":5,"scalinghealth:chance_heart":10,"farmersdelight:straw":2,"immersive_melodies:trumpet":1,"minecraft:player_head":10,"silentgems:alexandrite_glowrose":4,"minecraft:lectern":1,"minecraft:sugar_cane":204,"minecraft:spruce_trapdoor":2,"minecraft:raw_iron":58,"minecraft:stripped_mangrove_wood":2,"iceandfire:dragonscales_green":94,"minecraft:copper_ingot":1,"minecraft:bowl":1,"minecraft:polished_blackstone_bricks":33,"minecraft:trident":1,"alexsmobs:leafcutter_ant_pupa":1,"gobber2:gobber2_globette_nether":2,"minecraft:arrow":75,"minecraft:nether_bricks":1,"mutantmonsters:mutant_skeleton_rib":3,"minecraft:saddle":3,"minecraft:black_banner":9,"relics:reflection_necklace":1,"minecraft:skeleton_skull":6,"iceandfire:armor_black_chestplate":1,"born_in_chaos_v1:fused_bone":3,"mowziesmobs:umvuthana_mask_fury":1,"born_in_chaos_v1:corpse_maggot":40,"silentgear:flax_seeds":4,"minecraft:jungle_boat":2,"minecraft:basalt":4,"artifacts:novelty_drinking_hat":1,"minecraft:glow_ink_sac":1,"minecraft:crimson_stem":1,"gobber2:gobber2_gooey_beefstew":8,"minecraft:leather":57,"alexscaves:limestone":322,"minecraft:chainmail_chestplate":3,"iceandfire:ectoplasm":1,"minecraft:yellow_bed":1,"minecraft:cobbled_deepslate_stairs":1,"minecraft:gunpowder":10,"scalinghealth:heart_crystal":28,"minecraft:smooth_sandstone":13,"minecraft:silverfish_spawn_egg":1,"minecraft:iron_ingot":97,"minecraft:cooked_chicken":4,"minecraft:stripped_oak_wood":6,"alexscaves:curly_fern":4,"iceandfire:fire_dragon_flesh":2,"mowziesmobs:umvuthana_mask_misery":6,"minecraft:soul_sand":17,"minecraft:book":72,"minecraft:oak_slab":3,"minecraft:pink_bed":1,"scalinghealth:heart_crystal_shard":42,"graveyard:pedestal":2,"minecraft:bamboo_planks":1,"minecraft:pumpkin":6,"iceandfire:ash":4,"minecraft:quartz":3,"minecraft:dandelion":6,"minecraft:dripstone_block":14,"alexscaves:tree_star":2,"minecraft:blast_furnace":2,"minecraft:white_bed":2,"undead_revamp2:chiseleddripstonepillartop":3,"minecraft:spider_eye":3,"minecraft:stripped_jungle_log":3,"minecraft:pumpkin_seeds":3,"minecraft:chainmail_leggings":3,"minecraft:iron_helmet":6,"silentgear:sword_blueprint":1,"tombstone:magic_scroll":1,"majruszsdifficulty:tattered_chestplate":5,"silentgems:topaz":14,"minecraft:coal":36,"silentgear:sword":1},"minecraft:killed_by":{"minecraft:zombie_villager":4,"undead_revamp2:the_moonflower":6,"minecraft:piglin_brute":4,"hmag:fortress_keeper":1,"majruszsdifficulty:illusioner":1,"hmag:zombie_girl":1,"enemyexpansion:huntsman":1,"born_in_chaos_v1:siamese_skeletons":1,"minecraft:zombie":60,"majruszsdifficulty:cursed_armor":4,"enemyexpansion:invisicreeper":2,"minecraft:husk":27,"born_in_chaos_v1:restless_spirit":1,"minecraft:stray":1,"alexscaves:vallumraptor":2,"enemyexpansion:direwolf":2,"iceandfire:ghost":1,"born_in_chaos_v1:dread_hound":2,"undead_revamp2:sucker":1,"minecraft:zombified_piglin":2,"minecraft:wither_skeleton":3,"born_in_chaos_v1:mr_pumpkin":1,"minecraft:creeper":1,"born_in_chaos_v1:glutton_fish":1,"born_in_chaos_v1:zombie_bruiser":2,"born_in_chaos_v1:corpse_fly":1,"alexsmobs:elephant":1,"minecraft:drowned":1,"born_in_chaos_v1:diamond_termite":2,"cataclysm:deepling_brute":2,"minecraft:blaze":1,"artifacts:mimic":1,"graveyard:wraith":5,"iceandfire:fire_dragon":18,"alexscaves:tremorsaurus":1,"minecraft:player":48,"graveyard:ghoul":1,"minecraft:spider":2,"born_in_chaos_v1:senor_pumpkin":1,"minecraft:iron_golem":1,"enemyexpansion:equestrian":3,"minecraft:hoglin":1,"minecraft:skeleton":7,"iceandfire:lightning_dragon":3,"alexsmobs:crimson_mosquito":1,"graveyard:corrupted_vindicator":1,"hmag:necrotic_reaper":1,"born_in_chaos_v1:door_knight":1,"hmag:crimson_slaughterer":1},"minecraft:used":{"alexsmobs:emu_egg":1,"minecraft:moss_block":3,"silentgear:sword":942,"minecraft:ladder":1,"minecraft:chest":2,"graveyard:acacia_coffin":1,"minecraft:soul_sand":8,"hmag:exp_berry":7,"farmersdelight:fried_rice":1,"minecraft:bow":17,"iceandfire:chared_stone":1,"minecraft:oak_sapling":2,"minecraft:egg":88,"minecraft:mossy_stone_bricks":1,"minecraft:diorite":87,"minecraft:wooden_pickaxe":50,"minecraft:oak_leaves":1,"graveyard:skeleton_hand":3,"minecraft:golden_apple":5,"minecraft:sand":2,"minecraft:blast_furnace":2,"scalinghealth:cursed_heart":5,"mutantmonsters:mutant_skeleton_skull":1,"gobber2:gobber2_gooey_beefstew":2,"scalinghealth:enchanted_heart":4,"minecraft:zombie_head":2,"minecraft:lectern":1,"alexscaves:cycad":1,"minecraft:coal_block":1,"silentgear:saw":31,"born_in_chaos_v1:ethereal_spirit":11,"tombstone:scroll_of_frost_resistance":3,"born_in_chaos_v1:fried_maggot":1,"minecraft:netherrack":358,"silentgear:chestplate":8,"minecraft:torch":20,"minecraft:twisting_vines":4,"minecraft:shroomlight":1,"minecraft:iron_axe":45,"minecraft:smooth_quartz":1,"minecraft:barrel":3,"minecraft:bamboo":147,"minecraft:diamond_chestplate":8,"minecraft:basalt":4,"silentgear:pickaxe":748,"minecraft:beef":4,"tombstone:gift":8,"farmersdelight:cooking_pot":1,"minecraft:cobbled_deepslate":125,"silentgear:shield":14,"minecraft:wheat_seeds":7,"minecraft:yellow_banner":1,"minecraft:water_bucket":128,"minecraft:lead":1,"minecraft:cartography_table":1,"iceandfire:dragon_skull_lightning":4,"minecraft:polished_blackstone_bricks":33,"minecraft:tnt":22,"minecraft:crafting_table":5,"minecraft:white_bed":2,"mowziesmobs:wrought_axe":3,"minecraft:oak_log":1,"minecraft:diamond_pickaxe":993,"minecraft:acacia_sign":3,"minecraft:stripped_jungle_log":3,"iceandfire:dragonbone_sword_fire":962,"alexsmobs:kangaroo_meat":1,"minecraft:iron_pickaxe":245,"tombstone:magic_scroll":1,"minecraft:pink_bed":1,"minecraft:cobblestone":390,"minecraft:potion":6,"farmersdelight:cooked_bacon":2,"minecraft:porkchop":3,"minecraft:cooked_porkchop":11,"mowziesmobs:umvuthana_mask_fury":1,"minecraft:dandelion":3,"minecraft:candle":2,"gobber2:gobber2_gooey_beef_nether":1,"minecraft:iron_shovel":33,"gobber2:gobber2_gooey_bread":9,"minecraft:shield":75,"minecraft:iron_sword":9,"tombstone:lollipop":9,"graveyard:pedestal":1,"minecraft:player_head":9,"farmersdelight:melon_juice":1,"minecraft:jungle_planks":28,"minecraft:nether_bricks":1,"minecraft:carrot":87,"gobber2:gobber2_glass_nether":2,"minecraft:tuff":5,"minecraft:axolotl_bucket":3,"minecraft:milk_bucket":1,"born_in_chaos_v1:corpse_maggot":2,"minecraft:iron_helmet":3,"minecraft:mossy_cobblestone_slab":1,"born_in_chaos_v1:gnawed_bones":5,"minecraft:stone_bricks":1,"minecraft:item_frame":3,"minecraft:hay_block":10,"minecraft:skeleton_skull":2,"silentgems:ruby_glowrose":46,"dummmmmmy:target_dummy":2,"minecraft:stone_pickaxe":185,"minecraft:oak_planks":7,"minecraft:sandstone":1,"minecraft:diamond_axe":48,"minecraft:blue_bed":4,"minecraft:sugar_cane":5,"alexscaves:cave_book":10,"undead_revamp2:chiseled_dripstonepillar":2,"minecraft:black_banner":5,"minecraft:crossbow":13,"minecraft:cobbled_deepslate_stairs":1,"alexsmobs:terrapin_bucket":4,"hmag:fire_bottle":1,"minecraft:lever":3,"easy_villagers:villager":1,"farmersdelight:cooked_chicken_cuts":43,"minecraft:melon_slice":36,"minecraft:string":2,"minecraft:bread":115,"minecraft:cyan_bed":3,"tombstone:grave_key":213,"minecraft:jungle_sign":1,"iceandfire:dragon_skull_fire":1,"minecraft:chainmail_boots":1,"minecraft:cooked_rabbit":1,"minecraft:andesite":7,"minecraft:tropical_fish_bucket":2,"minecraft:bone_meal":18,"minecraft:experience_bottle":79,"graveyard:sarcophagus":6,"silentgems:sapphire_glowrose":1,"graveyard:candle_holder":6,"minecraft:trident":3,"sophisticatedbackpacks:iron_backpack":1,"mowziesmobs:umvuthana_mask_misery":2,"minecraft:redstone":1,"minecraft:cooked_chicken":2,"minecraft:dirt":102,"scalinghealth:heart_crystal":26,"iceandfire:armor_silver_metal_helmet":1,"minecraft:granite":15,"minecraft:iron_boots":1,"gobber2:gobber2_gooey_beef":3,"minecraft:golden_carrot":14,"alexsmobs:banana":2,"farmersdelight:cooked_mutton_chops":10,"minecraft:pumpkin":6,"minecraft:bamboo_planks":1,"minecraft:quartz_bricks":3,"iceandfire:fire_dragon_flesh":2,"minecraft:lodestone":1,"minecraft:baked_potato":2,"scalinghealth:chance_heart":10,"farmersdelight:onion":6,"graveyard:soul_fire_brazier":6,"born_in_chaos_v1:flaming_evil_pumpkin":1,"tombstone:bag_of_seeds":1,"minecraft:flower_pot":2,"minecraft:apple":1,"minecraft:chicken":7,"minecraft:cracked_polished_blackstone_bricks":2,"silentgear:hammer":229,"minecraft:stone_axe":138,"hmag:cureberry":4,"minecraft:white_banner":1,"minecraft:turtle_helmet":3,"iceandfire:armor_black_chestplate":1,"minecraft:bucket":140,"minecraft:yellow_bed":1,"alexsmobs:animal_dictionary":1,"minecraft:smooth_stone":1},"minecraft:broken":{"minecraft:golden_boots":1,"mowziesmobs:umvuthana_mask_faith":1,"majruszsdifficulty:tattered_boots":3,"minecraft:iron_boots":2,"majruszsdifficulty:tattered_leggings":4,"iceandfire:armor_black_chestplate":1,"minecraft:iron_chestplate":2,"minecraft:iron_leggings":4,"minecraft:chainmail_boots":3,"mowziesmobs:umvuthana_mask_fury":1,"minecraft:leather_helmet":2,"minecraft:chainmail_leggings":2,"minecraft:diamond_leggings":1,"minecraft:chainmail_helmet":1,"iceandfire:armor_silver_metal_helmet":1,"minecraft:shield":3,"minecraft:iron_pickaxe":1,"minecraft:iron_helmet":4,"minecraft:turtle_helmet":2,"minecraft:stone_pickaxe":1,"minecraft:chainmail_chestplate":1,"mowziesmobs:umvuthana_mask_bliss":1,"minecraft:diamond_chestplate":2,"minecraft:leather_chestplate":1,"mowziesmobs:umvuthana_mask_misery":2,"majruszsdifficulty:tattered_chestplate":2},"minecraft:custom":{"minecraft:interact_with_crafting_table":93,"minecraft:open_barrel":169,"minecraft:bell_ring":22,"minecraft:leave_game":39,"minecraft:time_since_death":14857,"minecraft:damage_blocked_by_shield":8056,"tombstone:eaten_lollipop":9,"minecraft:play_time":1524384,"minecraft:deaths":254,"tombstone:tomb_raiding":1,"minecraft:jump":25118,"minecraft:interact_with_furnace":10,"minecraft:traded_with_villager":153,"minecraft:interact_with_cartography_table":2,"minecraft:sleep_in_bed":30,"minecraft:waystone_activated":3,"tombstone:sneak_grave":46,"minecraft:damage_dealt":85502,"tombstone:undead_killed":93,"minecraft:interact_with_smoker":4,"minecraft:horse_one_cm":37128,"minecraft:use_cauldron":1,"minecraft:interact_with_anvil":3,"minecraft:damage_dealt_absorbed":10753,"minecraft:sneak_time":103203,"minecraft:interact_with_lectern":8,"minecraft:interact_with_blast_furnace":10,"minecraft:total_world_time":1524384,"tombstone:raider_killed":11,"minecraft:tune_noteblock":1,"minecraft:time_since_rest":10922,"minecraft:swim_one_cm":516492,"minecraft:fly_one_cm":5242389,"minecraft:open_chest":684,"minecraft:fall_one_cm":674007,"minecraft:damage_resisted":2623,"minecraft:sprint_one_cm":4251300,"minecraft:drop":669,"minecraft:interact_with_brewingstand":9,"minecraft:walk_on_water_one_cm":232659,"minecraft:interact_with_loom":14,"minecraft:player_kills":11,"minecraft:crouch_one_cm":315884,"minecraft:mob_kills":251,"minecraft:damage_dealt_resisted":35656,"minecraft:climb_one_cm":39775,"minecraft:walk_one_cm":2834899,"minecraft:walk_under_water_one_cm":102484,"minecraft:boat_one_cm":100158,"minecraft:pot_flower":2,"minecraft:damage_absorbed":270,"minecraft:damage_taken":177628,"minecraft:trigger_trapped_chest":12},"minecraft:dropped":{"minecraft:iron_sword":3,"iceandfire:raw_silver":1,"minecraft:stripped_mangrove_wood":2,"minecraft:glass_bottle":20,"minecraft:diamond":14,"minecraft:crafting_table":1,"minecraft:sandstone_stairs":3,"silentgems:rose_quartz_glowrose":8,"minecraft:crossbow":3,"minecraft:glow_berries":2,"silentgems:ruby":30,"farmersdelight:chicken_cuts":2,"iceandfire:ectoplasm":1,"minecraft:saddle":1,"silentgear:rough_rod":1,"artifacts:universal_attractor":3,"born_in_chaos_v1:nightmare_claw":2,"minecraft:item_frame":3,"sophisticatedbackpacks:gold_backpack":2,"born_in_chaos_v1:monster_flesh":4,"minecraft:dirt":85,"minecraft:packed_mud":1,"minecraft:dark_oak_fence":4,"artifacts:charm_of_sinking":1,"minecraft:jungle_sapling":9,"farmersdelight:cooked_mutton_chops":4,"minecraft:bone_meal":6,"minecraft:sand":1,"minecraft:sugar":28,"minecraft:iron_pickaxe":1,"majruszsdifficulty:tattered_leggings":2,"minecraft:bone":134,"minecraft:sugar_cane":1,"minecraft:lever":1,"alexsmobs:animal_dictionary":1,"minecraft:cobbled_deepslate":2142,"alexscaves:cave_tablet":4,"minecraft:obsidian":10,"undead_revamp2:arapholia":3,"tombstone:gift":1,"minecraft:rotten_flesh":183,"minecraft:oak_planks":8,"alexsmobs:emu_egg":1,"iceandfire:shiny_scales":47,"alexscaves:cave_book":4,"minecraft:quartz_block":16,"minecraft:jungle_log":45,"apotheosis:gem":33,"minecraft:campfire":2,"minecraft:egg":12,"minecraft:golden_boots":3,"minecraft:enchanted_book":2,"minecraft:iron_ingot":77,"minecraft:wheat_seeds":136,"silentgems:alexandrite_glowrose":3,"hmag:burning_core":1,"minecraft:golden_horse_armor":4,"minecraft:dripstone_block":3,"minecraft:feather":28,"minecraft:iron_helmet":4,"minecraft:cobblestone":1747,"minecraft:book":3,"minecraft:granite":7,"undead_revamp2:chiseleddripstonepillartop":3,"minecraft:bamboo_block":3,"minecraft:coal":1,"minecraft:cobweb":13,"born_in_chaos_v1:gnawed_bones":1,"iceandfire:copper_nugget":28,"alexscaves:limestone":261,"minecraft:jungle_boat":1,"graveyard:soul_fire_brazier":1,"minecraft:chainmail_leggings":3,"minecraft:iron_shovel":3,"minecraft:paper":22,"minecraft:string":62,"minecraft:smooth_sandstone":13,"silentgear:bort":4,"iceandfire:dragon_skull_fire":1,"silentgear:pickaxe":4,"hmag:soul_powder":5,"minecraft:player_head":3,"minecraft:cocoa_beans":10,"minecraft:bowl":2,"silentgems:citrine":3,"minecraft:experience_bottle":41,"minecraft:chicken":27,"minecraft:polished_deepslate_slab":1,"alexscaves:tree_star":1,"alexscaves:cave_codex":3,"minecraft:name_tag":4,"farmersdelight:straw":2,"minecraft:cobbled_deepslate_slab":3,"scalinghealth:power_crystal_shard":19,"silentgear:chestplate":4,"minecraft:hay_block":28,"minecraft:stone":12,"minecraft:flower_pot":2,"silentgear:saw_blueprint":2,"minecraft:spruce_trapdoor":2,"minecraft:bundle":5,"gobber2:gobber2_gooey_beef_nether":2,"easy_villagers:villager":3,"minecraft:bow":2,"waystones:waystone":1,"iceandfire:crackled_stone":10,"iceandfire:dragon_skull_lightning":3,"minecraft:quartz_slab":4,"boh:demonic_soul":2,"minecraft:oak_log":2,"minecraft:jungle_fence":1,"silentgems:topaz":12,"majruszsdifficulty:tattered_helmet":4,"minecraft:leather":26,"minecraft:jungle_planks":34,"minecraft:black_banner":2,"minecraft:flint":56,"tombstone:bag_of_seeds":1,"born_in_chaos_v1:monster_skin":1,"majruszsdifficulty:tattered_boots":1,"silentgear:crimson_iron_ingot":7,"farmersdelight:onion":5,"alexscaves:cave_map":1,"minecraft:axolotl_bucket":6,"minecraft:stripped_oak_wood":6,"minecraft:birch_log":2,"minecraft:gravel":4,"majruszsdifficulty:tattered_chestplate":3,"minecraft:silverfish_spawn_egg":2,"minecraft:smooth_sandstone_stairs":5,"minecraft:pointed_dripstone":2,"born_in_chaos_v1:ethereal_spirit":1,"minecraft:white_candle":2,"gobber2:gobber2_staff_ensnarement":1,"minecraft:carrot":1,"minecraft:chainmail_chestplate":1,"minecraft:sandstone_wall":17,"minecraft:leather_chestplate":3,"iceandfire:chain":3,"minecraft:turtle_helmet":1,"born_in_chaos_v1:seedof_chaos":5,"minecraft:gunpowder":5,"minecraft:skeleton_skull":2,"minecraft:melon_seeds":1,"born_in_chaos_v1:corpse_maggot":15,"minecraft:azalea":1,"minecraft:chest":1,"born_in_chaos_v1:diamond_termite_shard":5,"silentgear:leather_scrap":19,"minecraft:iron_bars":1,"minecraft:arrow":23,"minecraft:written_book":1,"minecraft:oak_leaves":4,"minecraft:netherrack":636,"minecraft:water_bucket":2,"minecraft:bread":74,"minecraft:oak_slab":3,"minecraft:golden_helmet":1,"minecraft:cherry_log":4,"gobber2:gobber2_foo":1,"iceandfire:dragonscales_green":47,"mowziesmobs:foliaath_seed":4,"minecraft:poisonous_potato":1,"scalinghealth:heart_crystal_shard":5,"born_in_chaos_v1:black_argillite_brick_slab":5,"silentgems:ruby_glowrose":50,"minecraft:copper_ingot":1,"minecraft:tropical_fish":1,"minecraft:grass_block":1,"minecraft:stick":9,"scalinghealth:medkit":1,"minecraft:diorite":65,"minecraft:torch":7,"scalinghealth:heart_crystal":3,"silentgear:shield":1,"tombstone:grave_key":6,"minecraft:melon_slice":12,"born_in_chaos_v1:fused_bone":3,"tombstone:grave_dust":62,"minecraft:wither_rose":1,"minecraft:iron_axe":2,"minecraft:chiseled_sandstone":1,"minecraft:dandelion":3,"minecraft:redstone":2,"minecraft:kelp":1,"silentgems:iolite":2,"minecraft:oak_trapdoor":5,"iceandfire:lightning_dragon_heart":2,"minecraft:raw_copper":26,"alexsmobs:tarantula_hawk_wing_fragment":2,"minecraft:tuff":31,"minecraft:raw_iron":2,"iceandfire:witherbone":1,"farmersdelight:cabbage_seeds":3,"iceandfire:dragonbone_sword_fire":1,"minecraft:comparator":1,"minecraft:filled_map":1,"iceandfire:rotten_egg":1,"farmersdelight:fried_egg":2,"mowziesmobs:umvuthana_mask_misery":5,"minecraft:andesite":16,"minecraft:golden_leggings":1,"minecraft:oak_sapling":7,"minecraft:golden_sword":1,"minecraft:slime_ball":6,"iceandfire:fire_dragon_heart":2,"minecraft:stone_pickaxe":1,"minecraft:wooden_pickaxe":5,"graveyard:sarcophagus":1}},"DataVersion":3465}